beancount2ledger/__init__.py
beancount2ledger/cli.py
beancount2ledger/common.py
beancount2ledger/hledger.py
beancount2ledger/ledger.py
beancount2ledger-1.3.data/data/share/man/man1/beancount2ledger.1
beancount2ledger-1.3.dist-info/LICENSE
beancount2ledger-1.3.dist-info/METADATA
beancount2ledger-1.3.dist-info/WHEEL
beancount2ledger-1.3.dist-info/entry_points.txt
beancount2ledger-1.3.dist-info/top_level.txt
beancount2ledger-1.3.dist-info/RECORD
